MANIFEST.in
README.rst
setup.py
docs/HISTORY.txt
docs/LICENSE.GPL
docs/LICENSE.txt
ftw/__init__.py
ftw.maintenanceserver.egg-info/PKG-INFO
ftw.maintenanceserver.egg-info/SOURCES.txt
ftw.maintenanceserver.egg-info/dependency_links.txt
ftw.maintenanceserver.egg-info/entry_points.txt
ftw.maintenanceserver.egg-info/namespace_packages.txt
ftw.maintenanceserver.egg-info/not-zip-safe
ftw.maintenanceserver.egg-info/requires.txt
ftw.maintenanceserver.egg-info/top_level.txt
ftw/maintenanceserver/__init__.py
ftw/maintenanceserver/server.py
ftw/maintenanceserver/testing.py
ftw/maintenanceserver/tests/__init__.py
ftw/maintenanceserver/tests/test_server.py
ftw/maintenanceserver/tests/htdocs/index.html
ftw/maintenanceserver/tests/htdocs/images/logo.png