Metadata-Version: 1.0
Name: ftw.maintenanceserver
Version: 1.0.2
Summary: Maintenance HTTP server, serving a static directory.
Home-page: https://github.com/4teamwork/ftw.maintenanceserver
Author: 4teamwork AG
Author-email: mailto:info@4teamwork.ch
License: GPL2
Keywords: ftw recipe maintenance
Platform: UNKNOWN
Classifier: Intended Audience :: Developers
Classifier: Topic :: Software Development :: Libraries :: Python Modules
